{"gameData":{"remit":[[{"id":23,"name":"Mexico","type":1,"displayName":"MEX"}],[{"id":26,"name":"Morocco","type":1,"displayName":"MAR"}],[{"id":160,"name":"Real Madrid","type":2,"displayName":"RMA"}],[{"id":172,"name":"Paris Saint-Germain","type":2,"displayName":"PSG"},{"id":83,"name":"AC Milan","type":2,"displayName":"MIL"}],[{"id":123,"name":"River Plate","type":2,"displayName":"RIV"}],[{"id":358,"name":"World Cup Top Scorer","type":6,"displayName":"World Cup Golden Boot","helperText":"data is available from 1958 onwards"}],[{"id":303,"name":"Carlo Ancelotti","type":4,"displayName":"Ancelotti","prefix":"Managed by"}],[{"id":314,"name":"Lionel Messi","type":5,"displayName":"Messi","prefix":"Played with"}],[{"id":357,"name":"Ballon d'Or","type":6,"displayName":"Ballon d'Or"}],[{"id":93,"name":"Liverpool","type":2,"displayName":"LIV"}],[{"id":336,"name":"Spanish League Top Scorer","type":6,"displayName":"LaLiga Golden Boot","helperText":"data is available from 1950/51 onwards"}],[{"id":612,"name":"Chinese League","type":3,"displayName":"Chinese League","helperText":"Had a spell at a club in China"}],[{"id":21,"name":"Chile","type":1,"displayName":"CHL"}],[{"id":29,"name":"Ghana","type":1,"displayName":"GHA"}],[{"id":550,"name":"Played in 3 of the 5 Big Leagues","type":8,"displayName":"3+ Big 5 Leagues","prefix":"Played in ","helperText":"has been a first-team squad member for clubs in at least 3 of Europe's Big 5 leagues (Premier League, La Liga, Bundesliga, Serie A, Ligue 1)."}],[{"id":37,"name":"Norway","type":1,"displayName":"NOR"}]],"players":[{"id":26172,"f":"Kudus","g":"Mohammed","v":[29]},{"id":1885,"f":"Pizarro","g":"David","v":[21]},{"id":4470,"f":"Klose","g":"Miroslav","v":[358]},{"id":4495,"f":"Rafinha","g":"","v":[303],"p":"RB"},{"id":20064,"f":"Dragusin","g":"Radu","v":[]},{"id":5665,"f":"Fuchs","g":"Christian","v":[]},{"id":1871,"f":"Kuffour","g":"Samuel","v":[29]},{"id":3073,"f":"Andrich","g":"Robert","v":[]},{"id":9249,"f":"Cucurella","g":"Marc","v":[]},{"id":61385,"f":"di Stefano","g":"Alfredo","v":[123,160,336,357]},{"id":940,"f":"Boateng","g":"Kevin-Prince","v":[29,83,314,550]},{"id":1399,"f":"Arshavin","g":"Andrey","v":[]},{"id":54440,"f":"Buchanan","g":"Tajon","v":[]},{"id":9153,"f":"Marquez","g":"Rafa","v":[23,314,550]},{"id":2474,"f":"Aguero","g":"Sergio","v":[314]},{"id":4943,"f":"Eto'o","g":"Samuel","v":[160,314,336,550]},{"id":5231,"f":"Mascherano","g":"Javier","v":[93,123,314,612]},{"id":1111,"f":"Maignan","g":"Mike","v":[83,172]},{"id":944,"f":"Ibrahimovic","g":"Zlatan","v":[83,172,303,314,550]},{"id":6797,"f":"Cambiasso","g":"Esteban","v":[123,160,314,550]},{"id":15313,"f":"Amrabat","g":"Sofyan","v":[26,550]},{"id":3471,"f":"Haller","g":"Sebastien","v":[550]},{"id":1426,"f":"Gervinho","g":"","v":[550,612]},{"id":42945,"f":"Hamsik","g":"Marek","v":[303,612]},{"id":27779,"f":"Sorloth","g":"Alexander","v":[37,550]},{"id":32558,"f":"Solskjaer","g":"Ole Gunnar","v":[37]},{"id":24045,"f":"Demiral","g":"Merih","v":[]},{"id":23305,"f":"Casillas","g":"Iker","v":[160,303]},{"id":26137,"f":"Ziyech","g":"Hakim","v":[26]},{"id":28668,"f":"Costa","g":"Diogo","v":[],"p":"GK"},{"id":5302,"f":"Luis Alberto","g":"","v":[93,550],"p":"CAM"},{"id":10501,"f":"Ben Yedder","g":"Wissam","v":[]},{"id":10423,"f":"Martial","g":"Anthony","v":[550]},{"id":1079,"f":"Higuain","g":"Gonzalo","v":[83,123,160,314,550]},{"id":2009,"f":"Rudiger","g":"Antonio","v":[160,303,550]},{"id":9581,"f":"Lloris","g":"Hugo","v":[]},{"id":4558,"f":"Coutinho","g":"Philippe","v":[93,314,550]},{"id":9567,"f":"Kane","g":"Harry","v":[358]},{"id":9551,"f":"Modric","g":"Luka","v":[83,160,303,357,550]},{"id":6957,"f":"Medel","g":"Gary","v":[21,550]},{"id":6816,"f":"Figo","g":"Luis","v":[160,357]},{"id":1400,"f":"Vela","g":"Carlos","v":[23]}]}}